setup.py
FF/BB.py
FF/BB_close.py
FF/PPPPP.py
FF/url_BL.py
FF/url_close.py
cmds.pp.egg-info/PKG-INFO
cmds.pp.egg-info/SOURCES.txt
cmds.pp.egg-info/dependency_links.txt
cmds.pp.egg-info/entry_points.txt
cmds.pp.egg-info/top_level.txt