Metadata-Version: 2.1
Name: cmds.pp
Version: 0.0.41
Summary: 笨笨貓 出版
Home-page: http://127.0.0.1:11184/
Author-email: login0516@gmail.com
License: MIT
